mitac_project/__init__.py
mitac_project/mitac.py
mitac_project-0.1.4.dist-info/METADATA
mitac_project-0.1.4.dist-info/WHEEL
mitac_project-0.1.4.dist-info/RECORD
