Metadata-Version: 2.3
Name: mitac-project
Version: 0.1.4
Summary: My Python library
License: MIT
Author: ff
Author-email: abc@gmail.com
Requires-Python: >=3.10
Classifier: License :: OSI Approved :: MIT License
Classifier: Programming Language :: Python :: 3
Classifier: Programming Language :: Python :: 3.10
Classifier: Programming Language :: Python :: 3.11
Classifier: Programming Language :: Python :: 3.12
Classifier: Programming Language :: Python :: 3.13
Requires-Dist: pandas (>=2.3.2,<3.0.0)
